arm_compare/__init__.py
arm_compare/arm_compare.py
azure_arm_compare-0.0.6.dist-info/LICENSE
azure_arm_compare-0.0.6.dist-info/METADATA
azure_arm_compare-0.0.6.dist-info/WHEEL
azure_arm_compare-0.0.6.dist-info/entry_points.txt
azure_arm_compare-0.0.6.dist-info/top_level.txt
azure_arm_compare-0.0.6.dist-info/RECORD
