Metadata-Version: 2.2
Name: azure-arm-compare
Version: 0.0.6
Summary: A tool to compare ARM templates (Azure).
Author-email: Phil Cartmell <phil@cartyio.onmicrosoft.com>
License: MIT License
Project-URL: Homepage, https://github.com/Philcartmell/azure-arm-compare
Requires-Python: >=3.6
License-File: LICENSE
Requires-Dist: pyyaml
Requires-Dist: openpyxl
